{
  "totalPage": 5,
  "currentPage": 1,
  "trades": [
    {
      "id": 127,
      "stockSymbol": "A",
      "companyName": "Agilent Tech",
      "created": "2016-03-14T04:30:45.433",
      "updated": "2016-03-18T19:35:23.44",
      "buyzoneStartPrice": 11.00,
      "buyzoneEndPrice": 22.00,
      "stopLossPrice": 1.00,
      "stopLossPercentage": 90.91,
      "gainLossPercentage": 0.0,
      "isTriggered": false,
      "isShort": true,
      "entryDate": null,
      "exitDate": null,
      "entryPrice": null,
      "exitPrice": null,
      "tradeSetupText": "123",
      "goalText": "123",
      "stopLossText": "123",
      "note": "123",
      "earningDueDate": "2016-05-16T00:00:00",
      "earningDueDateOption": 0,
      "earningDueDateEstimated": false,
      "imageId": 89,
      "state": 2
    },
    {
      "id": 126,
      "stockSymbol": "AA",
      "companyName": "Alcoa ",
      "created": "2016-03-14T03:37:40.717",
      "updated": "2016-03-18T19:36:19.41",
      "buyzoneStartPrice": 120.00,
      "buyzoneEndPrice": 130.00,
      "stopLossPrice": 118.80,
      "stopLossPercentage": 1.0,
      "gainLossPercentage": 0.0,
      "isTriggered": false,
      "isShort": true,
      "entryDate": null,
      "exitDate": null,
      "entryPrice": null,
      "exitPrice": null,
      "tradeSetupText": "123",
      "goalText": "312",
      "stopLossText": "111",
      "note": "111",
      "earningDueDate": "2016-04-08T00:00:00",
      "earningDueDateOption": 0,
      "earningDueDateEstimated": false,
      "imageId": 91,
      "state": 2
    },
    {
      "id": 129,
      "stockSymbol": "AAAP",
      "companyName": "Advanced Accelerator Applications",
      "created": "2016-03-14T07:25:12.443",
      "updated": "2016-03-18T19:34:40.883",
      "buyzoneStartPrice": 12.00,
      "buyzoneEndPrice": 20.00,
      "stopLossPrice": 5.00,
      "stopLossPercentage": 58.33,
      "gainLossPercentage": 0.0,
      "isTriggered": false,
      "isShort": true,
      "entryDate": null,
      "exitDate": null,
      "entryPrice": null,
      "exitPrice": null,
      "tradeSetupText": "123",
      "goalText": "123",
      "stopLossText": "123",
      "note": "123",
      "earningDueDate": "2016-03-14T00:00:00",
      "earningDueDateOption": 0,
      "earningDueDateEstimated": false,
      "imageId": 87,
      "state": 2
    },
    {
      "id": 223,
      "stockSymbol": "AAAP",
      "companyName": "Advanced Accelerator Applications",
      "created": "2016-03-23T07:21:11.127",
      "updated": "2016-03-23T09:20:51.353",
      "buyzoneStartPrice": 1.00,
      "buyzoneEndPrice": 111.00,
      "stopLossPrice": 0.98,
      "stopLossPercentage": 2.0,
      "gainLossPercentage": 0.0,
      "isTriggered": true,
      "isShort": false,
      "entryDate": "2016-03-23T07:21:20.793",
      "exitDate": "2016-03-23T09:20:51.353",
      "entryPrice": 36.80,
      "exitPrice": 36.80,
      "tradeSetupText": "12",
      "goalText": "12",
      "stopLossText": "12",
      "note": "12",
      "earningDueDate": "2016-03-23T00:00:00",
      "earningDueDateOption": 0,
      "earningDueDateEstimated": false,
      "imageId": 144,
      "state": 2
    },
    {
      "id": 222,
      "stockSymbol": "AAC",
      "companyName": "AAC",
      "created": "2016-03-23T07:18:26.36",
      "updated": "2016-03-23T09:21:35.507",
      "buyzoneStartPrice": 1.00,
      "buyzoneEndPrice": 111.00,
      "stopLossPrice": 0.98,
      "stopLossPercentage": 2.0,
      "gainLossPercentage": 0.0,
      "isTriggered": true,
      "isShort": false,
      "entryDate": "2016-03-23T07:18:28.867",
      "exitDate": "2016-03-23T09:21:35.507",
      "entryPrice": 19.17,
      "exitPrice": 19.17,
      "tradeSetupText": "12",
      "goalText": "12",
      "stopLossText": "12",
      "note": "12",
      "earningDueDate": "2016-03-23T00:00:00",
      "earningDueDateOption": 0,
      "earningDueDateEstimated": false,
      "imageId": 145,
      "state": 2
    },
    {
      "id": 166,
      "stockSymbol": "AAC",
      "companyName": "AAC",
      "created": "2016-03-18T04:01:40.66",
      "updated": "2016-03-18T16:37:53.68",
      "buyzoneStartPrice": 125.00,
      "buyzoneEndPrice": 126.00,
      "stopLossPrice": 126.25,
      "stopLossPercentage": 0.2,
      "gainLossPercentage": 0.0,
      "isTriggered": false,
      "isShort": false,
      "entryDate": null,
      "exitDate": null,
      "entryPrice": null,
      "exitPrice": null,
      "tradeSetupText": "This is to set up a text for trades",
      "goalText": "Goal is to earn money",
      "stopLossText": "no stop loss",
      "note": "sjfo",
      "earningDueDate": "2016-04-27T00:00:00",
      "earningDueDateOption": 0,
      "earningDueDateEstimated": false,
      "imageId": 60,
      "state": 2
    },
    {
      "id": 130,
      "stockSymbol": "AAC",
      "companyName": "AAC",
      "created": "2016-03-14T07:26:22.713",
      "updated": "2016-03-14T07:26:26.467",
      "buyzoneStartPrice": 12.00,
      "buyzoneEndPrice": 20.00,
      "stopLossPrice": 5.00,
      "stopLossPercentage": 58.33,
      "gainLossPercentage": 94.47,
      "isTriggered": true,
      "isShort": true,
      "entryDate": "2016-03-14T07:26:26.467",
      "exitDate": "2016-03-14T14:16:43.327",
      "entryPrice": 18.07,
      "exitPrice": 1.00,
      "tradeSetupText": "123",
      "goalText": "123",
      "stopLossText": "123",
      "note": "123",
      "earningDueDate": "2016-04-27T00:00:00",
      "earningDueDateOption": 0,
      "earningDueDateEstimated": false,
      "imageId": 45,
      "state": 2
    },
    {
      "id": 234,
      "stockSymbol": "AAN",
      "companyName": "Aaron's ",
      "created": "2016-03-24T02:57:30.727",
      "updated": "2016-03-25T05:09:47.167",
      "buyzoneStartPrice": 111.00,
      "buyzoneEndPrice": 1111.00,
      "stopLossPrice": 109.89,
      "stopLossPercentage": 1.0,
      "gainLossPercentage": 0.0,
      "isTriggered": false,
      "isShort": false,
      "entryDate": null,
      "exitDate": null,
      "entryPrice": null,
      "exitPrice": null,
      "tradeSetupText": "11",
      "goalText": "11",
      "stopLossText": "11",
      "note": "11",
      "earningDueDate": "2016-04-24T00:00:00",
      "earningDueDateOption": 0,
      "earningDueDateEstimated": false,
      "imageId": 152,
      "state": 2
    },
    {
      "id": 155,
      "stockSymbol": "AAON",
      "companyName": "AAON ",
      "created": "2016-03-15T05:57:36.107",
      "updated": "2016-03-15T09:43:58.427",
      "buyzoneStartPrice": 1111.00,
      "buyzoneEndPrice": 11111.00,
      "stopLossPrice": 111.00,
      "stopLossPercentage": 90.01,
      "gainLossPercentage": 0.0,
      "isTriggered": false,
      "isShort": false,
      "entryDate": null,
      "exitDate": null,
      "entryPrice": null,
      "exitPrice": null,
      "tradeSetupText": "111",
      "goalText": "111",
      "stopLossText": "111aa",
      "note": "111",
      "earningDueDate": "2016-05-05T00:00:00",
      "earningDueDateOption": 0,
      "earningDueDateEstimated": false,
      "imageId": 50,
      "state": 2
    },
    {
      "id": 111,
      "stockSymbol": "AAPL",
      "companyName": "Apple",
      "created": "2016-03-05T03:40:56.47",
      "updated": "2016-03-15T22:46:25.817",
      "buyzoneStartPrice": 90.00,
      "buyzoneEndPrice": 110.00,
      "stopLossPrice": 80.00,
      "stopLossPercentage": 11.11,
      "gainLossPercentage": 1.52,
      "isTriggered": true,
      "isShort": false,
      "entryDate": "2016-03-05T03:50:37.957",
      "exitDate": "2016-03-15T22:46:25.817",
      "entryPrice": 103.01,
      "exitPrice": 104.58,
      "tradeSetupText": "This is the text that appears on Trade Setup. The text should get cut off at 20 words in desktop and at 10 words in mobile. Testing the text display",
      "goalText": "Sell at 15% profit which equates to 114.75",
      "stopLossText": "Sell if the price falls below 5% of buy price, 87.5",
      "note": "This is the note text for APPL.",
      "earningDueDate": "2016-03-09T00:00:00",
      "earningDueDateOption": 0,
      "earningDueDateEstimated": false,
      "imageId": 55,
      "state": 2
    },
    {
      "id": 30,
      "stockSymbol": "ABEV",
      "companyName": "Ambev SA",
      "created": "2016-02-02T10:49:41.987",
      "updated": null,
      "buyzoneStartPrice": 2.88,
      "buyzoneEndPrice": 12.88,
      "stopLossPrice": 0.00,
      "stopLossPercentage": 7.0,
      "gainLossPercentage": 347.22222222,
      "isTriggered": true,
      "isShort": false,
      "entryDate": "2016-01-20T07:04:00.677",
      "exitDate": "2016-01-28T07:04:00.677",
      "entryPrice": 2.88,
      "exitPrice": 12.88,
      "tradeSetupText": "Aliquam massa lectus, bibendum sed sodales nec, tempus vitae dolor. Maecenas molestie mi eget quam iaculis, quis cursus orci bibendum. Aenean posuere ",
      "goalText": "Nullam varius velit dictum vestibulum aliquam. Vestibulum ac tristique lectus. Nulla facilisi. Pellentesque ut est et elit luctus maximus quis ut leo.",
      "stopLossText": "Etiam volutpat eu ligula non auctor. Maecenas nulla enim, hendrerit sed tortor at, aliquet ullamcorper arcu. Morbi dignissim, mauris vel euismod tempo",
      "note": "Mauris eget tortor congue, pretium lectus at, molestie risus. Nam purus libero, varius quis nunc quis, maximus consectetur justo. Curabitur lectus ant",
      "earningDueDate": "2016-02-16T00:00:00",
      "earningDueDateOption": 0,
      "earningDueDateEstimated": false,
      "imageId": -1,
      "state": 2
    },
    {
      "id": 125,
      "stockSymbol": "AEHR",
      "companyName": "Aehr Test Systems",
      "created": "2016-03-14T03:27:24.88",
      "updated": "2016-03-18T19:36:01.85",
      "buyzoneStartPrice": 11.00,
      "buyzoneEndPrice": 11.00,
      "stopLossPrice": 8.58,
      "stopLossPercentage": 22.0,
      "gainLossPercentage": 0.0,
      "isTriggered": false,
      "isShort": false,
      "entryDate": null,
      "exitDate": null,
      "entryPrice": null,
      "exitPrice": null,
      "tradeSetupText": "13wqseqwe",
      "goalText": "test add trade",
      "stopLossText": "sasd",
      "note": "a",
      "earningDueDate": "2016-03-26T00:00:00",
      "earningDueDateOption": 0,
      "earningDueDateEstimated": false,
      "imageId": 90,
      "state": 2
    },
    {
      "id": 173,
      "stockSymbol": "AHS",
      "companyName": "AMN Healthcare",
      "created": "2016-03-21T15:17:30.903",
      "updated": "2016-03-21T15:36:04.67",
      "buyzoneStartPrice": 32.35,
      "buyzoneEndPrice": 33.00,
      "stopLossPrice": 31.92,
      "stopLossPercentage": 1.33,
      "gainLossPercentage": 0.0,
      "isTriggered": false,
      "isShort": false,
      "entryDate": null,
      "exitDate": null,
      "entryPrice": null,
      "exitPrice": null,
      "tradeSetupText": "Eight-day consolidation as medical staffer builds right side of larger base.",
      "goalText": "10% gain or first decisive close below 5-day moving average. ",
      "stopLossText": "Cut loss if AHS takes out the 31.33 low of March 18 breakout day. ",
      "note": null,
      "earningDueDate": "2016-05-06T00:00:00",
      "earningDueDateOption": 0,
      "earningDueDateEstimated": false,
      "imageId": 98,
      "state": 2
    },
    {
      "id": 62,
      "stockSymbol": "AKER",
      "companyName": "Akers Biosciences",
      "created": "2016-01-31T10:49:41.987",
      "updated": null,
      "buyzoneStartPrice": 3.39,
      "buyzoneEndPrice": 13.39,
      "stopLossPrice": 0.00,
      "stopLossPercentage": 8.0,
      "gainLossPercentage": 0.0,
      "isTriggered": false,
      "isShort": false,
      "entryDate": null,
      "exitDate": null,
      "entryPrice": null,
      "exitPrice": null,
      "tradeSetupText": "Proin tincidunt mi at lacus dictum, ut malesuada nulla luctus. Nulla sit amet euismod mauris. Aenean lacinia ullamcorper turpis, at sodales orci maxim",
      "goalText": "Vestibulum at vestibulum mi. Duis viverra nunc sed commodo maximus. Mauris vel lobortis sapien. Fusce viverra iaculis orci nec congue. Pellentesque si",
      "stopLossText": "Maecenas ex mi, ullamcorper eu diam at, mattis aliquet arcu. Sed sit amet ex vitae justo accumsan ultricies. Fusce commodo sapien in imperdiet laoreet",
      "note": "Nulla pellentesque lobortis molestie. Suspendisse fringilla magna ornare, interdum nibh faucibus, interdum urna. Curabitur iaculis eu nisl in luctus. ",
      "earningDueDate": null,
      "earningDueDateOption": 0,
      "earningDueDateEstimated": false,
      "imageId": -1,
      "state": 2
    },
    {
      "id": 91,
      "stockSymbol": "ALKS",
      "companyName": "Alkermes",
      "created": "2016-01-31T10:49:41.987",
      "updated": null,
      "buyzoneStartPrice": 32.69,
      "buyzoneEndPrice": 42.69,
      "stopLossPrice": 0.00,
      "stopLossPercentage": 9.0,
      "gainLossPercentage": -23.42468962,
      "isTriggered": true,
      "isShort": false,
      "entryDate": "2016-01-20T07:04:00.677",
      "exitDate": "2016-01-28T07:04:00.677",
      "entryPrice": 42.69,
      "exitPrice": 32.69,
      "tradeSetupText": "Vivamus cursus suscipit nulla, quis sollicitudin risus euismod eu. Suspendisse sollicitudin mauris ut sem venenatis ultricies id id libero. Sed nunc f",
      "goalText": "Sed vitae diam ipsum. Integer malesuada euismod tempus. Nulla semper iaculis sem, quis ornare arcu commodo sit amet. Phasellus sed lacinia tellus. Qui",
      "stopLossText": "Pellentesque rhoncus, elit et sodales sagittis, velit tellus feugiat augue, eu gravida diam nisl in turpis. Suspendisse eu risus imperdiet libero rutr",
      "note": "Mauris id porta augue. Sed congue rhoncus turpis ut scelerisque. Mauris blandit venenatis tortor et rhoncus. Suspendisse non consectetur purus. Nunc a",
      "earningDueDate": "2016-02-16T00:00:00",
      "earningDueDateOption": 0,
      "earningDueDateEstimated": false,
      "imageId": -1,
      "state": 2
    },
    {
      "id": 93,
      "stockSymbol": "AMD",
      "companyName": "Advanced Micro Devices",
      "created": "2016-02-16T14:17:47.9",
      "updated": "2016-02-20T13:59:01.513",
      "buyzoneStartPrice": 1.90,
      "buyzoneEndPrice": 2.90,
      "stopLossPrice": 1.70,
      "stopLossPercentage": 0.0,
      "gainLossPercentage": -57.068062827225134,
      "isTriggered": true,
      "isShort": true,
      "entryDate": "2016-02-20T13:59:01.513",
      "exitDate": "2016-02-25T09:15:19.24",
      "entryPrice": 1.91,
      "exitPrice": 3.00,
      "tradeSetupText": "fsafasfsadfsaff a fdsafsa fdsafdsa f asdfasf",
      "goalText": "fsa fdsafsda fdsa fdsaf sadf s",
      "stopLossText": "fasdfasd fdsaf  sadfdsa fsaf sa",
      "note": "fjdlas fjdalfklj fadsfljkl fsdaljf fljasdlf flsdjafljas",
      "earningDueDate": null,
      "earningDueDateOption": 0,
      "earningDueDateEstimated": false,
      "imageId": 8,
      "state": 2
    },
    {
      "id": 68,
      "stockSymbol": "AMD",
      "companyName": "Advanced Micro Devices",
      "created": "2016-02-02T10:49:41.987",
      "updated": null,
      "buyzoneStartPrice": 1.09,
      "buyzoneEndPrice": 11.09,
      "stopLossPrice": 0.00,
      "stopLossPercentage": 7.0,
      "gainLossPercentage": 917.43119266,
      "isTriggered": true,
      "isShort": false,
      "entryDate": "2016-01-20T07:04:00.677",
      "exitDate": "2016-01-28T07:04:00.677",
      "entryPrice": 1.09,
      "exitPrice": 11.09,
      "tradeSetupText": "Morbi pellentesque neque a enim imperdiet, venenatis dapibus tortor molestie. Cras vel eros eu arcu finibus maximus ac ut massa. Praesent vel lorem in",
      "goalText": "Vestibulum in condimentum lacus. Quisque lorem leo, venenatis eu lectus nec, ullamcorper ultricies risus. Curabitur sed elementum leo, non tincidunt q",
      "stopLossText": "Quisque sapien turpis, tincidunt eu massa vel, pharetra fermentum ligula. Fusce elementum rhoncus hendrerit. Nullam mattis maximus turpis, id convalli",
      "note": "Donec pretium quam ac semper ornare. Etiam purus sapien, tristique et ligula quis, placerat blandit risus. Donec elementum pharetra rhoncus. Nulla bib",
      "earningDueDate": "2016-02-16T00:00:00",
      "earningDueDateOption": 0,
      "earningDueDateEstimated": false,
      "imageId": -1,
      "state": 2
    },
    {
      "id": 95,
      "stockSymbol": "AMZN",
      "companyName": "Amazon.com",
      "created": "2016-02-17T17:45:24.333",
      "updated": "2016-02-17T17:45:24.333",
      "buyzoneStartPrice": 550.00,
      "buyzoneEndPrice": 562.00,
      "stopLossPrice": 540.00,
      "stopLossPercentage": 5.0,
      "gainLossPercentage": 0.0,
      "isTriggered": false,
      "isShort": false,
      "entryDate": null,
      "exitDate": null,
      "entryPrice": null,
      "exitPrice": null,
      "tradeSetupText": "Trade Setup text for Amazon.com Stock. The stock is not in buy zone yet but creating a trade",
      "goalText": "Goal is to make 8% profit on this stock",
      "stopLossText": "Sell if the stock falls below 540",
      "note": null,
      "earningDueDate": null,
      "earningDueDateOption": 0,
      "earningDueDateEstimated": false,
      "imageId": -1,
      "state": 2
    },
    {
      "id": 98,
      "stockSymbol": "AMZN",
      "companyName": "Amazon.com",
      "created": "2016-02-25T09:39:30.887",
      "updated": "2016-02-25T09:39:36.767",
      "buyzoneStartPrice": 550.00,
      "buyzoneEndPrice": 570.00,
      "stopLossPrice": 540.00,
      "stopLossPercentage": 10.0,
      "gainLossPercentage": 1.08,
      "isTriggered": true,
      "isShort": false,
      "entryDate": "2016-02-25T09:39:36.767",
      "exitDate": "2016-02-25T09:41:19.387",
      "entryPrice": 554.04,
      "exitPrice": 560.00,
      "tradeSetupText": "This is trade setup text.",
      "goalText": "This is goal text.",
      "stopLossText": "This is stop loss text.",
      "note": "This is note.",
      "earningDueDate": "2016-02-29T00:00:00",
      "earningDueDateOption": 0,
      "earningDueDateEstimated": false,
      "imageId": 10,
      "state": 2
    },
    {
      "id": 110,
      "stockSymbol": "AMZN",
      "companyName": "Amazon.com",
      "created": "2016-03-05T03:23:25.837",
      "updated": "2016-03-15T22:45:19.443",
      "buyzoneStartPrice": 570.00,
      "buyzoneEndPrice": 580.00,
      "stopLossPrice": 560.03,
      "stopLossPercentage": 1.75,
      "gainLossPercentage": 0.33,
      "isTriggered": true,
      "isShort": false,
      "entryDate": "2016-03-05T03:50:37.847",
      "exitDate": "2016-03-15T22:45:19.427",
      "entryPrice": 575.14,
      "exitPrice": 577.02,
      "tradeSetupText": "Trade Setup Text Trade Setup Text Trade Setup Text",
      "goalText": "Goal Text Goal Text Goal Text",
      "stopLossText": "Stop Loss Text Stop Loss Text Stop Loss Text",
      "note": "Note Note Note",
      "earningDueDate": "2016-03-17T00:00:00",
      "earningDueDateOption": 0,
      "earningDueDateEstimated": false,
      "imageId": 54,
      "state": 2
    },
    {
      "id": 246,
      "stockSymbol": "AMZN",
      "companyName": "Amazon.com",
      "created": "2016-03-24T22:37:08.073",
      "updated": "2016-03-28T07:18:42.017",
      "buyzoneStartPrice": 120.00,
      "buyzoneEndPrice": 125.00,
      "stopLossPrice": 114.00,
      "stopLossPercentage": 5.0,
      "gainLossPercentage": 0.0,
      "isTriggered": false,
      "isShort": false,
      "entryDate": null,
      "exitDate": null,
      "entryPrice": null,
      "exitPrice": null,
      "tradeSetupText": "Test",
      "goalText": "test",
      "stopLossText": "Test",
      "note": "test",
      "earningDueDate": "2016-04-22T00:00:00",
      "earningDueDateOption": 0,
      "earningDueDateEstimated": false,
      "imageId": 154,
      "state": 2
    },
    {
      "id": 33,
      "stockSymbol": "ANY",
      "companyName": "Sphere 3D",
      "created": "2016-01-31T10:49:41.987",
      "updated": null,
      "buyzoneStartPrice": 3.24,
      "buyzoneEndPrice": 13.24,
      "stopLossPrice": 0.00,
      "stopLossPercentage": 5.0,
      "gainLossPercentage": 0.0,
      "isTriggered": false,
      "isShort": false,
      "entryDate": null,
      "exitDate": null,
      "entryPrice": null,
      "exitPrice": null,
      "tradeSetupText": "Nunc tincidunt nibh fringilla pulvinar pharetra. Vivamus laoreet risus quis dolor cursus, fringilla sagittis sapien sollicitudin. In non elit odio. Ve",
      "goalText": "Duis tristique, orci sed ornare euismod, lorem lorem cursus sem, eget finibus tellus leo non erat. Pellentesque maximus nulla eros, ac rhoncus magna a",
      "stopLossText": "Fusce ultrices, eros nec scelerisque aliquet, est augue blandit mi, sed facilisis massa turpis vitae nisi. Etiam lacinia bibendum eleifend. Ut sapien ",
      "note": "Curabitur sed turpis a ipsum convallis ultrices. Sed tortor sem, venenatis vel odio id, maximus pharetra tortor. Cras malesuada quam ut arcu pretium, ",
      "earningDueDate": null,
      "earningDueDateOption": 0,
      "earningDueDateEstimated": false,
      "imageId": -1,
      "state": 2
    },
    {
      "id": 1,
      "stockSymbol": "AZUR",
      "companyName": "Azure Midstream",
      "created": "2016-01-31T10:49:41.983",
      "updated": null,
      "buyzoneStartPrice": 1.29,
      "buyzoneEndPrice": 11.29,
      "stopLossPrice": 0.00,
      "stopLossPercentage": 7.0,
      "gainLossPercentage": -200.0,
      "isTriggered": true,
      "isShort": true,
      "entryDate": "2016-01-20T07:04:00.677",
      "exitDate": "2016-01-28T07:04:00.677",
      "entryPrice": 1.29,
      "exitPrice": 3.87,
      "tradeSetupText": "Integer ullamcorper ornare interdum. Praesent eget feugiat mauris. Nunc nulla libero, porttitor quis nisi et, gravida elementum dui. Morbi lobortis, o",
      "goalText": "Morbi varius lobortis scelerisque. Maecenas et aliquet ipsum. Nunc nec elementum eros. Interdum et malesuada fames ac ante ipsum primis in faucibus. A",
      "stopLossText": "Vestibulum in quam felis. Etiam eu porttitor elit. Donec porta, lectus quis imperdiet placerat, nisi nunc blandit justo, id tincidunt massa enim finib",
      "note": "In sem dui, congue vitae posuere pulvinar, porttitor ac odio. Nullam placerat ex eget diam viverra, in pharetra est maximus. Vestibulum imperdiet sem ",
      "earningDueDate": "2016-02-16T00:00:00",
      "earningDueDateOption": 0,
      "earningDueDateEstimated": false,
      "imageId": -1,
      "state": 2
    },
    {
      "id": 43,
      "stockSymbol": "BABA",
      "companyName": "Alibaba ",
      "created": "2016-01-31T10:49:41.987",
      "updated": null,
      "buyzoneStartPrice": 69.72,
      "buyzoneEndPrice": 79.72,
      "stopLossPrice": 60.00,
      "stopLossPercentage": 7.0,
      "gainLossPercentage": 14.74,
      "isTriggered": true,
      "isShort": false,
      "entryDate": "2016-02-03T00:00:00",
      "exitDate": "2016-03-01T07:06:40.067",
      "entryPrice": 69.72,
      "exitPrice": 80.00,
      "tradeSetupText": "Ut eu leo nisl. Pellentesque faucibus ipsum sed lectus varius ultricies. Mauris ornare laoreet mi quis hendrerit. Morbi sit amet tortor orci. Donec el",
      "goalText": "In auctor magna quis tortor interdum ultrices. Quisque gravida vel dui a pulvinar. Fusce ultricies odio non tempor luctus. Cras dapibus sem quis sodal",
      "stopLossText": "Duis pretium condimentum felis, in sagittis nulla dictum a. Aenean eget dui libero. Integer dignissim mi ac purus egestas pharetra. Nunc nec est quis ",
      "note": "Aliquam eu placerat quam, non scelerisque lectus. Nulla vulputate neque elit, vel sodales orci aliquet et. Proin at tellus tincidunt orci elementum mo",
      "earningDueDate": "2016-02-16T00:00:00",
      "earningDueDateOption": 0,
      "earningDueDateEstimated": false,
      "imageId": 12,
      "state": 2
    },
    {
      "id": 104,
      "stockSymbol": "BABA",
      "companyName": "Alibaba ",
      "created": "2016-03-02T09:05:50.12",
      "updated": "2016-03-18T19:37:51.63",
      "buyzoneStartPrice": 60.00,
      "buyzoneEndPrice": 80.00,
      "stopLossPrice": 50.00,
      "stopLossPercentage": 16.67,
      "gainLossPercentage": -5.44,
      "isTriggered": true,
      "isShort": true,
      "entryDate": "2016-03-05T03:50:37.217",
      "exitDate": "2016-03-18T19:37:51.63",
      "entryPrice": 72.22,
      "exitPrice": 76.15,
      "tradeSetupText": "Trade Setup Text Trade Setup Text Trade Setup Text Trade Setup Text",
      "goalText": "Goal Text Goal Text Goal Text Goal Text",
      "stopLossText": "Stop Loss Text Stop Loss Text Stop Loss Text Stop Loss Text",
      "note": "Note Note Note Updated on 03/16.",
      "earningDueDate": "2016-03-26T00:00:00",
      "earningDueDateOption": 0,
      "earningDueDateEstimated": false,
      "imageId": 95,
      "state": 2
    },
    {
      "id": 313,
      "stockSymbol": "BABA",
      "companyName": "Alibaba ",
      "created": "2016-04-04T17:14:03.987",
      "updated": "2016-04-06T10:04:01.79",
      "buyzoneStartPrice": 80.00,
      "buyzoneEndPrice": 81.60,
      "stopLossPrice": 80.48,
      "stopLossPercentage": 0.6,
      "gainLossPercentage": 0.0,
      "isTriggered": false,
      "isShort": false,
      "entryDate": null,
      "exitDate": null,
      "entryPrice": null,
      "exitPrice": null,
      "tradeSetupText": "Test Test",
      "goalText": "Test Test",
      "stopLossText": "Test Test TEST TEST TEST ",
      "note": null,
      "earningDueDate": "2016-04-28T00:00:00",
      "earningDueDateOption": 1,
      "earningDueDateEstimated": false,
      "imageId": 1200,
      "state": 2
    },
    {
      "id": 362,
      "stockSymbol": "BABA",
      "companyName": "Alibaba",
      "created": "2016-04-25T05:57:14.1",
      "updated": "2016-04-26T16:53:29.473",
      "buyzoneStartPrice": 79.00,
      "buyzoneEndPrice": 80.58,
      "stopLossPrice": 78.00,
      "stopLossPercentage": -1.27,
      "gainLossPercentage": 1.07,
      "isTriggered": true,
      "isShort": false,
      "entryDate": "2016-04-25T05:57:38.74",
      "exitDate": "2016-04-26T16:53:29.303",
      "entryPrice": 79.15,
      "exitPrice": 80.00,
      "tradeSetupText": "Trade Setup TextTrade Setup TextTrade Setup Text",
      "goalText": "Goal Text",
      "stopLossText": "Stop Loss Text",
      "note": "Note (For internal use only) ",
      "earningDueDate": "2016-05-07T00:00:00",
      "earningDueDateOption": 0,
      "earningDueDateEstimated": true,
      "imageId": 1227,
      "state": 2
    },
    {
      "id": 114,
      "stockSymbol": "BAC",
      "companyName": "Bank Of America Corp",
      "created": "2016-03-08T09:46:10.187",
      "updated": "2016-03-08T09:46:12.28",
      "buyzoneStartPrice": 10.00,
      "buyzoneEndPrice": 20.00,
      "stopLossPrice": 8.00,
      "stopLossPercentage": 20.0,
      "gainLossPercentage": 10.86,
      "isTriggered": true,
      "isShort": false,
      "entryDate": "2016-03-08T09:46:12.28",
      "exitDate": "2016-03-09T05:34:09.81",
      "entryPrice": 13.53,
      "exitPrice": 15.00,
      "tradeSetupText": "Trade Setup Text",
      "goalText": "Goal Text",
      "stopLossText": "Stop Loss Text",
      "note": "Note Note Note",
      "earningDueDate": "2016-04-15T00:00:00",
      "earningDueDateOption": 0,
      "earningDueDateEstimated": false,
      "imageId": 34,
      "state": 2
    },
    {
      "id": 51,
      "stockSymbol": "BAC",
      "companyName": "Bank Of America Corp",
      "created": "2016-01-31T10:49:41.987",
      "updated": null,
      "buyzoneStartPrice": 12.36,
      "buyzoneEndPrice": 22.36,
      "stopLossPrice": 0.00,
      "stopLossPercentage": 8.0,
      "gainLossPercentage": 80.90614886,
      "isTriggered": true,
      "isShort": false,
      "entryDate": "2016-01-20T07:04:00.677",
      "exitDate": "2016-01-28T07:04:00.677",
      "entryPrice": 12.36,
      "exitPrice": 22.36,
      "tradeSetupText": "Vestibulum vulputate magna eu nisi interdum, ut ultrices nulla tincidunt. Etiam porta mi leo, non malesuada metus tincidunt eu. In finibus, libero vel",
      "goalText": "Pellentesque fringilla metus in laoreet pulvinar. Aliquam vehicula, mauris eget vehicula volutpat, erat neque posuere tellus, eget rhoncus lorem nulla",
      "stopLossText": "Suspendisse faucibus odio nec magna efficitur, et aliquam risus ultricies. Mauris vitae pharetra ex. Interdum et malesuada fames ac ante ipsum primis ",
      "note": "Cras quis imperdiet mauris, non volutpat arcu. Sed lobortis erat lacus, et tempor orci finibus quis. Nulla ac suscipit lacus. Proin tempor nibh ac lib",
      "earningDueDate": "2016-02-16T00:00:00",
      "earningDueDateOption": 0,
      "earningDueDateEstimated": false,
      "imageId": -1,
      "state": 2
    },
    {
      "id": 224,
      "stockSymbol": "BBBY",
      "companyName": "Bed Bath & Beyond",
      "created": "2016-03-23T07:24:44.84",
      "updated": "2016-03-23T09:17:30.567",
      "buyzoneStartPrice": 11.00,
      "buyzoneEndPrice": 111.00,
      "stopLossPrice": 10.78,
      "stopLossPercentage": 2.0,
      "gainLossPercentage": 0.0,
      "isTriggered": true,
      "isShort": false,
      "entryDate": "2016-03-23T07:24:49.013",
      "exitDate": "2016-03-23T09:17:30.567",
      "entryPrice": 50.17,
      "exitPrice": 50.17,
      "tradeSetupText": "Trade Setup Text",
      "goalText": "This a gola.",
      "stopLossText": "CCC",
      "note": "DDD",
      "earningDueDate": "2016-04-08T00:00:00",
      "earningDueDateOption": 0,
      "earningDueDateEstimated": false,
      "imageId": 143,
      "state": 2
    },
    {
      "id": 247,
      "stockSymbol": "BBD",
      "companyName": "Banco Bradesco SA",
      "created": "2016-03-25T10:06:44.21",
      "updated": "2016-04-06T12:59:01.68",
      "buyzoneStartPrice": 100.00,
      "buyzoneEndPrice": 200.00,
      "stopLossPrice": 70.00,
      "stopLossPercentage": -30.0,
      "gainLossPercentage": 0.0,
      "isTriggered": false,
      "isShort": false,
      "entryDate": null,
      "exitDate": null,
      "entryPrice": null,
      "exitPrice": null,
      "tradeSetupText": "11",
      "goalText": "11",
      "stopLossText": "11",
      "note": "11",
      "earningDueDate": "2016-03-25T00:00:00",
      "earningDueDateOption": 0,
      "earningDueDateEstimated": true,
      "imageId": 1206,
      "state": 2
    },
    {
      "id": 227,
      "stockSymbol": "BBEP",
      "companyName": "Breitburn Energy",
      "created": "2016-03-23T08:16:56.617",
      "updated": "2016-03-23T09:07:46.857",
      "buyzoneStartPrice": 0.10,
      "buyzoneEndPrice": 11111.00,
      "stopLossPrice": 0.10,
      "stopLossPercentage": 1.0,
      "gainLossPercentage": 0.12,
      "isTriggered": true,
      "isShort": false,
      "entryDate": "2016-03-23T08:18:04.947",
      "exitDate": "2016-03-23T09:07:46.857",
      "entryPrice": 0.80,
      "exitPrice": 0.80,
      "tradeSetupText": "1",
      "goalText": "1",
      "stopLossText": "1",
      "note": "1",
      "earningDueDate": "2016-05-05T00:00:00",
      "earningDueDateOption": 0,
      "earningDueDateEstimated": false,
      "imageId": 142,
      "state": 2
    },
    {
      "id": 172,
      "stockSymbol": "BIDU",
      "companyName": "Baidu ",
      "created": "2016-03-21T12:01:04.797",
      "updated": "2016-03-23T05:29:48.227",
      "buyzoneStartPrice": 100.00,
      "buyzoneEndPrice": 210.00,
      "stopLossPrice": 252.00,
      "stopLossPercentage": 20.0,
      "gainLossPercentage": -0.68,
      "isTriggered": true,
      "isShort": true,
      "entryDate": "2016-03-22T11:20:13.65",
      "exitDate": "2016-03-23T05:29:48.223",
      "entryPrice": 187.12,
      "exitPrice": 188.40,
      "tradeSetupText": "jlfjdlsa fjsdalf ",
      "goalText": "fdjlasdf fasdljf ",
      "stopLossText": "fdjslaf fasdfjla ",
      "note": "dfjlsa fdsadf asd",
      "earningDueDate": "2016-04-29T00:00:00",
      "earningDueDateOption": 0,
      "earningDueDateEstimated": false,
      "imageId": 124,
      "state": 2
    },
    {
      "id": 386,
      "stockSymbol": "BIDU",
      "companyName": "Baidu ",
      "created": "2016-05-17T08:49:23.74",
      "updated": "2016-06-28T18:25:05.427",
      "buyzoneStartPrice": 160.00,
      "buyzoneEndPrice": 163.20,
      "stopLossPrice": 150.00,
      "stopLossPercentage": -6.25,
      "gainLossPercentage": -6.56,
      "isTriggered": true,
      "isShort": false,
      "entryDate": "2016-06-13T13:33:14.757",
      "exitDate": "2016-06-28T18:25:05.427",
      "entryPrice": 160.53,
      "exitPrice": 150.00,
      "tradeSetupText": "aaab",
      "goalText": "bb",
      "stopLossText": "ccc",
      "note": "ddd",
      "earningDueDate": "2016-07-27T00:00:00",
      "earningDueDateOption": 0,
      "earningDueDateEstimated": true,
      "imageId": 1237,
      "state": 2
    },
    {
      "id": 343,
      "stockSymbol": "BIDU",
      "companyName": "Baidu           ",
      "created": "2016-04-07T06:33:10.697",
      "updated": "2016-04-26T23:44:15.487",
      "buyzoneStartPrice": 160.00,
      "buyzoneEndPrice": 200.00,
      "stopLossPrice": 140.00,
      "stopLossPercentage": -12.5,
      "gainLossPercentage": 0.79,
      "isTriggered": true,
      "isShort": false,
      "entryDate": "2016-04-07T06:33:42.77",
      "exitDate": "2016-04-26T23:44:15.343",
      "entryPrice": 186.77,
      "exitPrice": 188.25,
      "tradeSetupText": "Test",
      "goalText": "Test",
      "stopLossText": "Test",
      "note": "Test",
      "earningDueDate": "2016-04-27T00:00:00",
      "earningDueDateOption": 0,
      "earningDueDateEstimated": false,
      "imageId": 1228,
      "state": 2
    },
    {
      "id": 101,
      "stockSymbol": "BIDU",
      "companyName": "Baidu ",
      "created": "2016-02-26T07:53:01.317",
      "updated": "2016-03-18T19:38:19.98",
      "buyzoneStartPrice": 150.00,
      "buyzoneEndPrice": 170.00,
      "stopLossPrice": 140.00,
      "stopLossPercentage": 10.0,
      "gainLossPercentage": 19.11,
      "isTriggered": true,
      "isShort": false,
      "entryDate": "2016-02-26T07:53:05.867",
      "exitDate": "2016-03-18T19:38:19.98",
      "entryPrice": 158.22,
      "exitPrice": 188.46,
      "tradeSetupText": "Trade Setup Text Trade Setup Text Trade Setup Text Trade Setup Text",
      "goalText": "Goal Text Goal Text Goal Text Goal Text",
      "stopLossText": "Stop Loss Text Stop Loss Text Stop Loss Text",
      "note": "Note Note Note Note Note Note Note Note Note Note",
      "earningDueDate": "2016-02-29T00:00:00",
      "earningDueDateOption": 0,
      "earningDueDateEstimated": false,
      "imageId": 96,
      "state": 2
    },
    {
      "id": 96,
      "stockSymbol": "BIDU",
      "companyName": "Baidu ",
      "created": "2016-02-22T14:28:41.153",
      "updated": "2016-02-22T14:52:08.383",
      "buyzoneStartPrice": 165.00,
      "buyzoneEndPrice": 170.00,
      "stopLossPrice": 163.00,
      "stopLossPercentage": 1.0,
      "gainLossPercentage": -19.724633343310387,
      "isTriggered": true,
      "isShort": true,
      "entryDate": "2016-02-22T14:52:08.383",
      "exitDate": "2016-02-25T08:41:33.327",
      "entryPrice": 167.05,
      "exitPrice": 200.00,
      "tradeSetupText": "This is to test the trade setup text.This is to test the trade setup text.",
      "goalText": "This is to test the goal test. This is to test the goal test. ",
      "stopLossText": "This is to test the stop loss text. This is to test the stop loss text. ",
      "note": "Please note this is a test data.",
      "earningDueDate": "2016-02-26T00:00:00",
      "earningDueDateOption": 0,
      "earningDueDateEstimated": false,
      "imageId": 6,
      "state": 2
    },
    {
      "id": 97,
      "stockSymbol": "BIDU",
      "companyName": "Baidu ",
      "created": "2016-02-25T08:45:45.477",
      "updated": "2016-02-25T08:45:48.587",
      "buyzoneStartPrice": 160.00,
      "buyzoneEndPrice": 170.00,
      "stopLossPrice": 155.00,
      "stopLossPercentage": 10.0,
      "gainLossPercentage": 84.33,
      "isTriggered": true,
      "isShort": false,
      "entryDate": "2016-02-25T08:45:48.587",
      "exitDate": "2016-02-25T08:55:56.607",
      "entryPrice": 162.75,
      "exitPrice": 300.00,
      "tradeSetupText": "TEst",
      "goalText": "TEst",
      "stopLossText": "Test",
      "note": "TEst",
      "earningDueDate": "2016-02-26T00:00:00",
      "earningDueDateOption": 0,
      "earningDueDateEstimated": false,
      "imageId": 7,
      "state": 2
    },
    {
      "id": 174,
      "stockSymbol": "BRKR",
      "companyName": "Bruker Corp",
      "created": "2016-03-21T15:30:44.033",
      "updated": "2016-03-23T05:31:01.977",
      "buyzoneStartPrice": 26.60,
      "buyzoneEndPrice": 28.15,
      "stopLossPrice": 25.68,
      "stopLossPercentage": 3.44,
      "gainLossPercentage": 0.76,
      "isTriggered": true,
      "isShort": false,
      "entryDate": "2016-03-22T11:23:45.31",
      "exitDate": "2016-03-23T05:31:01.977",
      "entryPrice": 27.46,
      "exitPrice": 27.67,
      "tradeSetupText": "Stock reverses after pulling back from recent 29.23 high. ",
      "goalText": "10% gain or first decisive close below 5-day moving average. ",
      "stopLossText": "Cut loss is BRKR undercuts 26.66 low of March 18 reversal day. ",
      "note": null,
      "earningDueDate": "2016-05-06T00:00:00",
      "earningDueDateOption": 0,
      "earningDueDateEstimated": false,
      "imageId": 126,
      "state": 2
    },
    {
      "id": 83,
      "stockSymbol": "BRZU",
      "companyName": "DirexBzlBll3",
      "created": "2016-01-31T10:49:41.987",
      "updated": null,
      "buyzoneStartPrice": 5.65,
      "buyzoneEndPrice": 15.65,
      "stopLossPrice": 0.00,
      "stopLossPercentage": 7.0,
      "gainLossPercentage": 63.897763578274763,
      "isTriggered": true,
      "isShort": true,
      "entryDate": "2016-01-20T07:04:00.677",
      "exitDate": "2016-01-28T07:04:00.677",
      "entryPrice": 15.65,
      "exitPrice": 5.65,
      "tradeSetupText": "Morbi scelerisque massa lacinia magna gravida, eget suscipit erat tempus. Ut ut ex venenatis, tempor elit et, accumsan nisi. Proin neque est, imperdie",
      "goalText": "Sed posuere commodo vehicula. Morbi efficitur id quam vel accumsan. Praesent ultrices ante et ligula hendrerit, id lobortis justo vehicula. Sed id ips",
      "stopLossText": "Integer cursus sed neque sed gravida. Donec dapibus tempor dolor et congue. Phasellus non suscipit ipsum, at mollis massa. Nulla blandit convallis vel",
      "note": "Fusce posuere odio vitae magna accumsan ornare. Duis dictum purus in felis egestas, non ullamcorper nibh suscipit. Donec ut massa felis. Proin id eges",
      "earningDueDate": "2016-02-16T00:00:00",
      "earningDueDateOption": 0,
      "earningDueDateEstimated": false,
      "imageId": -1,
      "state": 2
    },
    {
      "id": 56,
      "stockSymbol": "BSET",
      "companyName": "Bassett Furniture Inds",
      "created": "2016-01-31T10:49:41.987",
      "updated": null,
      "buyzoneStartPrice": 28.37,
      "buyzoneEndPrice": 38.37,
      "stopLossPrice": 0.00,
      "stopLossPercentage": 7.0,
      "gainLossPercentage": 35.24850193,
      "isTriggered": true,
      "isShort": false,
      "entryDate": "2016-01-20T07:04:00.677",
      "exitDate": "2016-01-28T07:04:00.677",
      "entryPrice": 28.37,
      "exitPrice": 38.37,
      "tradeSetupText": "Sed dictum magna a magna tincidunt, non ullamcorper ex condimentum. Aliquam ultrices ex eget turpis tristique accumsan ut eu quam. Sed in massa pretiu",
      "goalText": "Nulla non facilisis dui, non hendrerit velit. Maecenas dolor tellus, sagittis vel neque id, mattis consectetur ante. Class aptent taciti sociosqu ad l",
      "stopLossText": "Nam eget orci vestibulum, interdum risus quis, semper ipsum. Quisque elementum mauris nec posuere eleifend. Sed interdum turpis a venenatis lobortis. ",
      "note": "Donec id iaculis erat, ultrices eleifend arcu. Donec erat justo, mattis id interdum vitae, placerat sed nisi. Integer scelerisque cursus finibus. Cras",
      "earningDueDate": "2016-02-16T00:00:00",
      "earningDueDateOption": 0,
      "earningDueDateEstimated": false,
      "imageId": -1,
      "state": 2
    },
    {
      "id": 18,
      "stockSymbol": "BTE",
      "companyName": "Baytex Energy Corp",
      "created": "2016-01-31T10:49:41.987",
      "updated": null,
      "buyzoneStartPrice": 0.68,
      "buyzoneEndPrice": 10.68,
      "stopLossPrice": 0.00,
      "stopLossPercentage": 5.0,
      "gainLossPercentage": -1470.5882352941178,
      "isTriggered": true,
      "isShort": true,
      "entryDate": "2016-01-20T07:04:00.677",
      "exitDate": "2016-01-28T07:04:00.677",
      "entryPrice": 0.68,
      "exitPrice": 10.68,
      "tradeSetupText": "Proin congue convallis pulvinar. Sed vestibulum arcu eu elit facilisis interdum. Sed eu ex velit. Cras dolor nunc, maximus vel varius quis, efficitur ",
      "goalText": "Vestibulum eu ipsum purus. Quisque malesuada fringilla nisi. Nullam at ornare enim. Quisque lobortis sagittis quam, ac iaculis lacus scelerisque sit a",
      "stopLossText": "Sed leo tortor, consequat eu risus sed, rhoncus condimentum augue. Sed venenatis tortor quis arcu pellentesque dapibus. Etiam lacus sem, tincidunt id ",
      "note": "In sollicitudin aliquam justo. Quisque et imperdiet ante. Praesent lobortis sem malesuada viverra blandit. Aliquam ac velit eu velit egestas mollis in",
      "earningDueDate": "2016-02-16T00:00:00",
      "earningDueDateOption": 0,
      "earningDueDateEstimated": false,
      "imageId": -1,
      "state": 2
    },
    {
      "id": 20,
      "stockSymbol": "C",
      "companyName": "Citigroup",
      "created": "2016-01-31T10:49:41.987",
      "updated": null,
      "buyzoneStartPrice": 42.15,
      "buyzoneEndPrice": 52.15,
      "stopLossPrice": 0.00,
      "stopLossPercentage": 5.0,
      "gainLossPercentage": 0.0,
      "isTriggered": false,
      "isShort": false,
      "entryDate": null,
      "exitDate": null,
      "entryPrice": null,
      "exitPrice": null,
      "tradeSetupText": "Nullam eleifend malesuada mi ac suscipit. Proin ut diam in nisi porta interdum. Vestibulum ullamcorper nunc nibh, eu placerat lectus rutrum gravida. C",
      "goalText": "Sed mollis lorem porta nulla ullamcorper feugiat. Sed luctus, risus sed vehicula gravida, turpis magna maximus felis, sed lacinia erat felis lobortis ",
      "stopLossText": "Aliquam euismod mi nec eros dictum, vitae consectetur dui fermentum. Nam mattis sem neque, eu blandit felis rhoncus eu. Donec faucibus gravida imperdi",
      "note": "Vestibulum tristique tempus dictum. Integer augue nisl, fermentum rutrum odio eu, lacinia porta lectus. Nullam vel sagittis mi. Suspendisse vehicula, ",
      "earningDueDate": null,
      "earningDueDateOption": 0,
      "earningDueDateEstimated": false,
      "imageId": -1,
      "state": 2
    },
    {
      "id": 132,
      "stockSymbol": "C",
      "companyName": "Citigroup",
      "created": "2016-03-14T07:31:57.817",
      "updated": "2016-03-18T19:34:24.273",
      "buyzoneStartPrice": 12.00,
      "buyzoneEndPrice": 20.00,
      "stopLossPrice": 5.00,
      "stopLossPercentage": 58.33,
      "gainLossPercentage": 0.0,
      "isTriggered": false,
      "isShort": true,
      "entryDate": null,
      "exitDate": null,
      "entryPrice": null,
      "exitPrice": null,
      "tradeSetupText": "123",
      "goalText": "123",
      "stopLossText": "123",
      "note": "123",
      "earningDueDate": "2016-04-15T00:00:00",
      "earningDueDateOption": 0,
      "earningDueDateEstimated": false,
      "imageId": 86,
      "state": 2
    },
    {
      "id": 133,
      "stockSymbol": "CA",
      "companyName": "CA",
      "created": "2016-03-14T07:35:24.167",
      "updated": "2016-03-18T19:34:05.21",
      "buyzoneStartPrice": 12.00,
      "buyzoneEndPrice": 20.00,
      "stopLossPrice": 5.00,
      "stopLossPercentage": 58.33,
      "gainLossPercentage": 0.0,
      "isTriggered": false,
      "isShort": true,
      "entryDate": null,
      "exitDate": null,
      "entryPrice": null,
      "exitPrice": null,
      "tradeSetupText": "123",
      "goalText": "123",
      "stopLossText": "123",
      "note": "123",
      "earningDueDate": "2016-05-05T00:00:00",
      "earningDueDateOption": 0,
      "earningDueDateEstimated": false,
      "imageId": 85,
      "state": 2
    },
    {
      "id": 134,
      "stockSymbol": "CAAS",
      "companyName": "China Automotive Systems",
      "created": "2016-03-14T07:37:20.783",
      "updated": "2016-03-18T19:33:48.76",
      "buyzoneStartPrice": 12.00,
      "buyzoneEndPrice": 20.00,
      "stopLossPrice": 5.00,
      "stopLossPercentage": 58.33,
      "gainLossPercentage": 0.0,
      "isTriggered": false,
      "isShort": true,
      "entryDate": null,
      "exitDate": null,
      "entryPrice": null,
      "exitPrice": null,
      "tradeSetupText": "123",
      "goalText": "123",
      "stopLossText": "123",
      "note": "123",
      "earningDueDate": "2016-03-26T00:00:00",
      "earningDueDateOption": 0,
      "earningDueDateEstimated": false,
      "imageId": 84,
      "state": 2
    },
    {
      "id": 135,
      "stockSymbol": "CABO",
      "companyName": "Cable One",
      "created": "2016-03-14T07:39:12.61",
      "updated": "2016-03-18T19:32:24.563",
      "buyzoneStartPrice": 20.00,
      "buyzoneEndPrice": 26.00,
      "stopLossPrice": 19.00,
      "stopLossPercentage": 5.0,
      "gainLossPercentage": 0.0,
      "isTriggered": false,
      "isShort": true,
      "entryDate": null,
      "exitDate": null,
      "entryPrice": null,
      "exitPrice": null,
      "tradeSetupText": "11",
      "goalText": "111",
      "stopLossText": "11",
      "note": "111",
      "earningDueDate": "2016-04-28T00:00:00",
      "earningDueDateOption": 0,
      "earningDueDateEstimated": false,
      "imageId": 83,
      "state": 2
    },
    {
      "id": 136,
      "stockSymbol": "CACC",
      "companyName": "Credit Acceptance Corp",
      "created": "2016-03-14T08:21:24.963",
      "updated": "2016-03-14T08:21:32.677",
      "buyzoneStartPrice": 111.00,
      "buyzoneEndPrice": 1111.00,
      "stopLossPrice": 11.00,
      "stopLossPercentage": 90.09,
      "gainLossPercentage": -3.31,
      "isTriggered": true,
      "isShort": true,
      "entryDate": "2016-03-14T08:21:32.677",
      "exitDate": "2016-03-14T09:31:40.657",
      "entryPrice": 203.27,
      "exitPrice": 210.00,
      "tradeSetupText": "111",
      "goalText": "111",
      "stopLossText": "111",
      "note": "111",
      "earningDueDate": "2016-04-27T00:00:00",
      "earningDueDateOption": 0,
      "earningDueDateEstimated": false,
      "imageId": 43,
      "state": 2
    },
    {
      "id": 92,
      "stockSymbol": "CATYW",
      "companyName": "Cathay General Bancorp",
      "created": "2016-01-31T10:49:41.987",
      "updated": null,
      "buyzoneStartPrice": 8.99,
      "buyzoneEndPrice": 18.99,
      "stopLossPrice": 0.00,
      "stopLossPercentage": 6.0,
      "gainLossPercentage": 0.0,
      "isTriggered": false,
      "isShort": true,
      "entryDate": null,
      "exitDate": null,
      "entryPrice": null,
      "exitPrice": null,
      "tradeSetupText": "Nullam aliquam mollis volutpat. Fusce ornare justo et neque ullamcorper, in mattis felis luctus. Maecenas vitae eleifend nisl. Curabitur vitae viverra",
      "goalText": "Morbi odio nisi, condimentum id eros sed, placerat pharetra elit. Nam vitae aliquet sapien. Phasellus scelerisque tortor dignissim massa laoreet, quis",
      "stopLossText": "Maecenas tempor odio vel consectetur venenatis. Sed in fermentum est, in scelerisque sem. Aliquam gravida finibus mollis. Nam in facilisis neque, eu v",
      "note": "Ut velit diam, rutrum et mi a, auctor blandit ex. Quisque sit amet lacinia enim. Maecenas quam massa, porta nec nulla ac, lacinia condimentum dolor. C",
      "earningDueDate": null,
      "earningDueDateOption": 0,
      "earningDueDateEstimated": false,
      "imageId": -1,
      "state": 2
    },
    {
      "id": 225,
      "stockSymbol": "CCA",
      "companyName": "MFS CaMnFd",
      "created": "2016-03-23T07:27:30.317",
      "updated": "2016-03-23T07:59:37.323",
      "buyzoneStartPrice": 11.00,
      "buyzoneEndPrice": 111.00,
      "stopLossPrice": 10.78,
      "stopLossPercentage": 2.0,
      "gainLossPercentage": 0.0,
      "isTriggered": true,
      "isShort": false,
      "entryDate": "2016-03-23T07:27:34.307",
      "exitDate": "2016-03-23T07:59:37.32",
      "entryPrice": 12.15,
      "exitPrice": 12.15,
      "tradeSetupText": "3",
      "goalText": "3",
      "stopLossText": "3",
      "note": "3",
      "earningDueDate": "2016-05-29T00:00:00",
      "earningDueDateOption": 0,
      "earningDueDateEstimated": false,
      "imageId": 139,
      "state": 2
    }
  ]
}